onnx2fmu/CMakeLists.txt
onnx2fmu/__init__.py
onnx2fmu/aarch64-linux-toolchain.cmake
onnx2fmu/app.py
onnx2fmu/config.py
onnx2fmu/model.py
onnx2fmu/model_description.py
onnx2fmu/variables.py
onnx2fmu/include/FMI.h
onnx2fmu/include/FMI1.h
onnx2fmu/include/FMI2.h
onnx2fmu/include/FMI3.h
onnx2fmu/include/cosimulation.h
onnx2fmu/include/fmi1Functions.h
onnx2fmu/include/fmi2FunctionTypes.h
onnx2fmu/include/fmi2Functions.h
onnx2fmu/include/fmi2TypesPlatform.h
onnx2fmu/include/fmi3FunctionTypes.h
onnx2fmu/include/fmi3Functions.h
onnx2fmu/include/fmi3PlatformTypes.h
onnx2fmu/include/fmiFunctions.h
onnx2fmu/include/fmiModelFunctions.h
onnx2fmu/include/fmiModelTypes.h
onnx2fmu/include/fmiPlatformTypes.h
onnx2fmu/include/model.h
onnx2fmu/include/ortUtils.h
onnx2fmu/include/structured_variable_name.tab.h
onnx2fmu/src/FMI.c
onnx2fmu/src/FMI1.c
onnx2fmu/src/FMI2.c
onnx2fmu/src/FMI3.c
onnx2fmu/src/README.md
onnx2fmu/src/cosimulation.c
onnx2fmu/src/fmi1Functions.c
onnx2fmu/src/fmi2Functions.c
onnx2fmu/src/fmi3Functions.c
onnx2fmu/src/ortUtils.c
onnx2fmu/src/structured_variable_name.l
onnx2fmu/src/structured_variable_name.tab.c
onnx2fmu/src/structured_variable_name.y
onnx2fmu/src/structured_variable_name.yy.c
onnx2fmu/template/FMI1CS.xml
onnx2fmu/template/FMI2.xml
onnx2fmu/template/FMI3.xml
onnx2fmu/template/buildDescription.xml
onnx2fmu/template/config.h
onnx2fmu/template/model.c
onnx2fmu/template/resources/y.txt
onnx2fmu-0.2.5.dist-info/entry_points.txt
onnx2fmu-0.2.5.dist-info/licenses/LICENSE.txt
onnx2fmu-0.2.5.dist-info/WHEEL
onnx2fmu-0.2.5.dist-info/METADATA
onnx2fmu-0.2.5.dist-info/RECORD
