Metadata-Version: 2.4
Name: onnx2fmu
Version: 0.2.5
Summary: A tool for wrapping ONNX netwroks in FMUs.
Author-email: Michele Urbani <murbani@fbk.eu>
Requires-Python: >=3.10
Classifier: Programming Language :: Python :: 3
Classifier: Programming Language :: Python :: 3.10
Classifier: Programming Language :: Python :: 3.11
Classifier: Programming Language :: Python :: 3.12
Classifier: License :: OSI Approved :: MIT License
Classifier: Operating System :: OS Independent
Classifier: Development Status :: 4 - Beta
Classifier: Topic :: Utilities
Classifier: Topic :: Scientific/Engineering
License-File: LICENSE.txt
Requires-Dist: onnx
Requires-Dist: jinja2
Requires-Dist: cmake
Requires-Dist: numpy
Requires-Dist: loguru
Requires-Dist: typer
Requires-Dist: pandas>=2.3.1
Requires-Dist: fmpy>=0.3.25
Requires-Dist: plotly>=6.3.1
